dephell_links-0.1.5.dist-info/dependency_links.txt
dephell_links-0.1.5.dist-info/entry_points.txt
dephell_links-0.1.5.dist-info/METADATA
dephell_links-0.1.5.dist-info/top_level.txt
dephell_links-0.1.5.dist-info/WHEEL
dephell_links/_parse.py
dephell_links/_cached_property.py
dephell_links/_constants.py
dephell_links/__init__.py
dephell_links/_url.py
dephell_links/_path.py
dephell_links/_vcs.py
dephell_links/_unknown.py
dephell_links-0.1.5.dist-info/LICENSE
dephell_links-0.1.5.dist-info/RECORD